IceSpringPathLib/IceSpringPathLib.py
IceSpringPathLib/IceSpringPathLib.pyi
IceSpringPathLib/IceSpringPathLib_cli.py
IceSpringPathLib/__init__.py
IceSpringPathLib/__init__conf__.py
IceSpringPathLib/_typeshed.pyi
IceSpringPathLib/typing_extensions.pyi
IceSpringPathLib-1.1.1.dist-info/METADATA
IceSpringPathLib-1.1.1.dist-info/WHEEL
IceSpringPathLib-1.1.1.dist-info/top_level.txt
IceSpringPathLib-1.1.1.dist-info/RECORD
