Metadata-Version: 2.1
Name: IceSpringPathLib
Version: 1.1.1
Summary: `pathlib` Wrapper with **UTF-8 first** and **LineFeed first**, based on `pathlib3x`.
Home-page: https://github.com/baijifeilong/IceSpringPathLib
Author: BaiJiFeiLong
Author-email: baijifeilong@gmail.com
License: MIT
Platform: UNKNOWN
